ganzo/__init__.py
ganzo/__main__.py
ganzo/cli.py
ganzo/core.py
ganzo/resolvers.py
ganzo/sources/__init__.py
ganzo/sources/gcs.py
ganzo/sources/git.py
ganzo/sources/local.py
ganzo-1.0.0.dist-info/LICENSE
ganzo-1.0.0.dist-info/METADATA
ganzo-1.0.0.dist-info/WHEEL
ganzo-1.0.0.dist-info/entry_points.txt
ganzo-1.0.0.dist-info/top_level.txt
ganzo-1.0.0.dist-info/RECORD
